{
  "playlists": [
    {
      "id": "pl_ai",
      "title": "AI",
      "desc": "Các video về AI",
      "items": [
        { "id": "ai1", "title": "AI có mơ chăng?", "url": "https://youtu.be/StFihkKIywo" }
      ]
    },
    {
      "id": "pl_nini",
      "title": "My music",
      "desc": "Nhạc relax",
      "items": [
        { "id": "001", "title": "Chàng trai latte", "url": "https://youtu.be/CgVKJmidfBk" },
        { "id": "002", "title": "Latte boy",   "url": "https://youtube.com/shorts/UoGg1a9pzLI" }
      ]
    }
  ]
}


